Metadata-Version: 1.1
Name: mitsuplccom
Version: 0.0.1
Summary: Library to communicate with FX5U PLC using socket communication
Home-page: UNKNOWN
Author: Robin Singla
Author-email: robinformal@gmail.com
License: MIT
Keywords: PLC
Platform: UNKNOWN
Classifier: Development Status :: 5 - Production/Stable
Classifier: Intended Audience :: Education
Classifier: Operating System :: Microsoft :: Windows :: Windows 10
Classifier: License :: OSI Approved :: MIT License
Classifier: Programming Language :: Python :: 3
